codehackscalculator/__init__.py
ode_hack-0.1.dist-info/LICENSE.txt
ode_hack-0.1.dist-info/METADATA
ode_hack-0.1.dist-info/WHEEL
ode_hack-0.1.dist-info/top_level.txt
ode_hack-0.1.dist-info/RECORD
