Metadata-Version: 2.1
Name: ode-hack
Version: 0.1
Summary: a basic calculator
Author: Anwyll Archie
Author-email: chakrabortysubhojeet01@gmail.com
Classifier: Programming Language :: Python :: 3
Classifier: License :: OSI Approved :: MIT License
Classifier: Operating System :: OS Independent
License-File: LICENSE.txt
